fast_manager/__init__.py
fast_manager-0.dist-info/LICENSE
fast_manager-0.dist-info/WHEEL
fast_manager-0.dist-info/METADATA
fast_manager-0.dist-info/RECORD
