Metadata-Version: 2.1
Name: fast-manager
Version: 0
Summary: Create Python Web Fast, Manage Easily
Home-page: https://github.com/0417taehyun/fast-manager
License: MIT
Author: weekwith.me
Author-email: leedobby@weekwith.me
Requires-Python: >=3.7,<4.0
Classifier: License :: OSI Approved :: MIT License
Classifier: Programming Language :: Python :: 3
Classifier: Programming Language :: Python :: 3 :: Only
Classifier: Programming Language :: Python :: 3.10
Classifier: Programming Language :: Python :: 3.7
Classifier: Programming Language :: Python :: 3.8
Classifier: Programming Language :: Python :: 3.9
Project-URL: Documentation, https://fastmanager.weekwith.me
Project-URL: Repository, https://github.com/0417taehyun/fast-manager
